{
  "project_info": {
    "project_number": "926854527593",
    "firebase_url": "https://webbiesimageurl.firebaseio.com",
    "project_id": "webbiesimageurl",
    "storage_bucket": "webbiesimageurl.appspot.com"
  },
  "client": [
    {
      "client_info": {
        "mobilesdk_app_id": "1:926854527593:android:48bf73f1c43ad582",
        "android_client_info": {
          "package_name": "com.example.webbiestest"
        }
      },
      "oauth_client": [
        {
          "client_id": "926854527593-lg9our500a4ttpie46v1clhl6fmrkgtl.apps.googleusercontent.com",
          "client_type": 3
        }
      ],
      "api_key": [
        {
          "current_key": "AIzaSyC4X5Sk1m213e_dutCBO9NjdJmW06s0Vl8"
        }
      ],
      "services": {
        "appinvite_service": {
          "other_platform_oauth_client": [
            {
              "client_id": "926854527593-lg9our500a4ttpie46v1clhl6fmrkgtl.apps.googleusercontent.com",
              "client_type": 3
            }
          ]
        }
      }
    }
  ],
  "configuration_version": "1"
}